moser_pylint-2.7.2.data/scripts/epylint
moser_pylint-2.7.2.data/scripts/pylint
moser_pylint-2.7.2.data/scripts/pyreverse
moser_pylint-2.7.2.data/scripts/symilar
pylint/__init__.py
pylint/__main__.py
pylint/__pkginfo__.py
pylint/config.py
pylint/constants.py
pylint/epylint.py
pylint/exceptions.py
pylint/graph.py
pylint/interfaces.py
pylint/lint.py
pylint/testutils.py
pylint/checkers/__init__.py
pylint/checkers/async.py
pylint/checkers/base.py
pylint/checkers/base_checker.py
pylint/checkers/classes.py
pylint/checkers/design_analysis.py
pylint/checkers/exceptions.py
pylint/checkers/format.py
pylint/checkers/imports.py
pylint/checkers/logging.py
pylint/checkers/misc.py
pylint/checkers/newstyle.py
pylint/checkers/python3.py
pylint/checkers/raw_metrics.py
pylint/checkers/refactoring.py
pylint/checkers/similar.py
pylint/checkers/spelling.py
pylint/checkers/stdlib.py
pylint/checkers/strings.py
pylint/checkers/typecheck.py
pylint/checkers/utils.py
pylint/checkers/variables.py
pylint/config/__init__.py
pylint/config/configuration_mixin.py
pylint/config/find_default_config_files.py
pylint/config/man_help_formatter.py
pylint/config/option.py
pylint/config/option_manager_mixin.py
pylint/config/option_parser.py
pylint/config/options_provider_mixin.py
pylint/extensions/__init__.py
pylint/extensions/_check_docs_utils.py
pylint/extensions/bad_builtin.py
pylint/extensions/broad_try_clause.py
pylint/extensions/check_docs.py
pylint/extensions/check_elif.py
pylint/extensions/comparetozero.py
pylint/extensions/docparams.py
pylint/extensions/docstyle.py
pylint/extensions/emptystring.py
pylint/extensions/mccabe.py
pylint/extensions/overlapping_exceptions.py
pylint/extensions/redefined_variable_type.py
pylint/lint/__init__.py
pylint/lint/check_parallel.py
pylint/lint/pylinter.py
pylint/lint/report_functions.py
pylint/lint/run.py
pylint/lint/utils.py
pylint/message/__init__.py
pylint/message/build_message_definition.py
pylint/message/message.py
pylint/message/message_definition.py
moser_pylint-2.7.2.dist-info/COPYING
moser_pylint-2.7.2.dist-info/METADATA
moser_pylint-2.7.2.dist-info/WHEEL
moser_pylint-2.7.2.dist-info/entry_points.txt
moser_pylint-2.7.2.dist-info/top_level.txt
moser_pylint-2.7.2.dist-info/RECORD
