Metadata-Version: 2.1
Name: moser-pylint
Version: 2.7.2
Summary: UNKNOWN
Home-page: https://github.com/moser/pylint
Author: Python Code Quality Authority
Author-email: code-quality@python.org
License: GPL
Project-URL: What's New, https://pylint.pycqa.org/en/latest/whatsnew/
Platform: UNKNOWN
Classifier: Development Status :: 6 - Mature
Classifier: Environment :: Console
Classifier: Intended Audience :: Developers
Classifier: License :: OSI Approved :: GNU General Public License (GPL)
Classifier: Operating System :: OS Independent
Classifier: Programming Language :: Python
Classifier: Programming Language :: Python :: 3
Classifier: Programming Language :: Python :: 3.5
Classifier: Programming Language :: Python :: 3.6
Classifier: Programming Language :: Python :: 3.7
Classifier: Programming Language :: Python :: 3.8
Classifier: Programming Language :: Python :: 3 :: Only
Classifier: Programming Language :: Python :: Implementation :: CPython
Classifier: Programming Language :: Python :: Implementation :: PyPy
Classifier: Topic :: Software Development :: Debuggers
Classifier: Topic :: Software Development :: Quality Assurance
Classifier: Topic :: Software Development :: Testing
Requires-Python: >=3.5.*
Requires-Dist: astroid (<=2.5,>=2.4.0)
Requires-Dist: isort (<5,>=4.2.5)
Requires-Dist: mccabe (<0.7,>=0.6)
Requires-Dist: toml (>=0.7.1)
Requires-Dist: colorama ; sys_platform=="win32"
